smart_c3p/__init__.py
smart_c3p/analyzer.py
smart_c3p/core.py
smart_c3p/pdf_parser.py
smart_c3p/report_generator.py
smart_c3p/utils.py
smart_c3p-0.1.1.dist-info/licenses/LICENSE
smart_c3p-0.1.1.dist-info/METADATA
smart_c3p-0.1.1.dist-info/WHEEL
smart_c3p-0.1.1.dist-info/top_level.txt
smart_c3p-0.1.1.dist-info/RECORD
