Metadata-Version: 2.4
Name: smart-c3p
Version: 0.1.1
Summary: Geração de relatórios analíticos com IA a partir de DataFrames e PDFs de regras de negócio.
Author-email: Gabriel <negociogabriel2k25@outlook.com>
License-File: LICENSE
Requires-Dist: pandas
Requires-Dist: matplotlib
Requires-Dist: pymupdf
Requires-Dist: reportlab
Dynamic: license-file
